odoo/addons/ssi_helpdesk_appointment/README.rst
odoo/addons/ssi_helpdesk_appointment/__init__.py
odoo/addons/ssi_helpdesk_appointment/__manifest__.py
odoo/addons/ssi_helpdesk_appointment/models/__init__.py
odoo/addons/ssi_helpdesk_appointment/models/helpdesk_ticket.py
odoo/addons/ssi_helpdesk_appointment/static/description/icon.png
odoo/addons/ssi_helpdesk_appointment/views/helpdesk_ticket_views.xml
odoo14_addon_ssi_helpdesk_appointment-14.0.1.0.0.dist-info/METADATA
odoo14_addon_ssi_helpdesk_appointment-14.0.1.0.0.dist-info/WHEEL
odoo14_addon_ssi_helpdesk_appointment-14.0.1.0.0.dist-info/top_level.txt
odoo14_addon_ssi_helpdesk_appointment-14.0.1.0.0.dist-info/RECORD
